{
  "$schema": "https://developer.microsoft.com/json-schemas/fabric/item/report/definition/visualContainer/2.3.0/schema.json",
  "name": "dc8efe7692ee418c6749",
  "position": {
    "x": 56.023708771403811,
    "y": 587.55430073284083,
    "z": 1000,
    "height": 57.133023210821165,
    "width": 77.403665808638053
  },
  "visual": {
    "visualType": "actionButton",
    "objects": {
      "icon": [
        {
          "properties": {
            "shapeType": {
              "expr": {
                "Literal": {
                  "Value": "'blank'"
                }
              }
            }
          },
          "selector": {
            "id": "default"
          }
        },
        {
          "properties": {
            "show": {
              "expr": {
                "Literal": {
                  "Value": "true"
                }
              }
            }
          }
        }
      ],
      "text": [
        {
          "properties": {
            "show": {
              "expr": {
                "Literal": {
                  "Value": "true"
                }
              }
            }
          }
        },
        {
          "properties": {
            "text": {
              "expr": {
                "Measure": {
                  "Expression": {
                    "SourceRef": {
                      "Entity": "measuretable"
                    }
                  },
                  "Property": "unicode_close_nav_pane"
                }
              }
            },
            "fontColor": {
              "solid": {
                "color": {
                  "expr": {
                    "ThemeDataColor": {
                      "ColorId": 4,
                      "Percent": 0
                    }
                  }
                }
              }
            },
            "fontSize": {
              "expr": {
                "Literal": {
                  "Value": "32D"
                }
              }
            }
          },
          "selector": {
            "id": "default"
          }
        }
      ],
      "outline": [
        {
          "properties": {
            "show": {
              "expr": {
                "Literal": {
                  "Value": "false"
                }
              }
            }
          }
        }
      ],
      "rotation": [
        {
          "properties": {
            "shapeAngle": {
              "expr": {
                "Literal": {
                  "Value": "0L"
                }
              }
            },
            "angle": {
              "expr": {
                "Literal": {
                  "Value": "270L"
                }
              }
            }
          }
        }
      ]
    },
    "visualContainerObjects": {
      "title": [
        {
          "properties": {
            "text": {
              "expr": {
                "Literal": {
                  "Value": "'navigation close'"
                }
              }
            },
            "titleWrap": {
              "expr": {
                "Literal": {
                  "Value": "true"
                }
              }
            }
          }
        }
      ],
      "visualLink": [
        {
          "properties": {
            "show": {
              "expr": {
                "Literal": {
                  "Value": "true"
                }
              }
            },
            "type": {
              "expr": {
                "Literal": {
                  "Value": "'Bookmark'"
                }
              }
            },
            "bookmark": {
              "expr": {
                "Literal": {
                  "Value": "'957314c4f2f2b6591a57'"
                }
              }
            },
            "tooltip": {
              "expr": {
                "Literal": {
                  "Value": "'back to main page'"
                }
              }
            }
          }
        }
      ],
      "background": [
        {
          "properties": {
            "show": {
              "expr": {
                "Literal": {
                  "Value": "true"
                }
              }
            },
            "color": {
              "solid": {
                "color": {
                  "expr": {
                    "Literal": {
                      "Value": "'#FFFFFF'"
                    }
                  }
                }
              }
            },
            "transparency": {
              "expr": {
                "Literal": {
                  "Value": "0D"
                }
              }
            }
          }
        }
      ],
      "border": [
        {
          "properties": {
            "show": {
              "expr": {
                "Literal": {
                  "Value": "false"
                }
              }
            },
            "radius": {
              "expr": {
                "Literal": {
                  "Value": "5D"
                }
              }
            }
          }
        }
      ],
      "dropShadow": [
        {
          "properties": {
            "show": {
              "expr": {
                "Literal": {
                  "Value": "false"
                }
              }
            }
          }
        }
      ],
      "visualTooltip": [
        {
          "properties": {
            "titleFontColor": {
              "solid": {
                "color": {
                  "expr": {
                    "Literal": {
                      "Value": "'#BEBEBE'"
                    }
                  }
                }
              }
            },
            "valueFontColor": {
              "solid": {
                "color": {
                  "expr": {
                    "Literal": {
                      "Value": "'#E8E8E8'"
                    }
                  }
                }
              }
            },
            "background": {
              "solid": {
                "color": {
                  "expr": {
                    "Literal": {
                      "Value": "'#787878'"
                    }
                  }
                }
              }
            }
          }
        }
      ],
      "visualHeaderTooltip": [
        {
          "properties": {
            "titleFontColor": {
              "solid": {
                "color": {
                  "expr": {
                    "Literal": {
                      "Value": "'#BEBEBE'"
                    }
                  }
                }
              }
            },
            "background": {
              "solid": {
                "color": {
                  "expr": {
                    "Literal": {
                      "Value": "'#787878'"
                    }
                  }
                }
              }
            }
          }
        }
      ]
    },
    "drillFilterOtherVisuals": true
  },
  "parentGroupName": "7d0068ea088f853007be"
}